firefox_open_tabs/__init__.py
firefox_open_tabs/firefox_open_tabs.py
firefox_open_tabs-0.1.0.dist-info/LICENSE
firefox_open_tabs-0.1.0.dist-info/METADATA
firefox_open_tabs-0.1.0.dist-info/WHEEL
firefox_open_tabs-0.1.0.dist-info/entry_points.txt
firefox_open_tabs-0.1.0.dist-info/top_level.txt
firefox_open_tabs-0.1.0.dist-info/RECORD
